{
    "%vlocity_namespace%__ApplicableSubType__c": "Profile Attribute",
    "%vlocity_namespace%__ApplicableTypesFilter__c": "",
    "%vlocity_namespace%__ApplicableTypes__c": "Account",
    "%vlocity_namespace%__Attribute__c": "Marks_Attributes.json",
    "%vlocity_namespace%__Code__c": "Marks",
    "%vlocity_namespace%__ColorCode__c": "",
    "%vlocity_namespace%__Description__c": "Test for Marks Management Epic",
    "%vlocity_namespace%__DisplayFilter__c": false,
    "%vlocity_namespace%__DisplaySequence__c": 999,
    "%vlocity_namespace%__EffectiveFromDate__c": "",
    "%vlocity_namespace%__EffectiveUntilDate__c": "",
    "%vlocity_namespace%__GlobalKey__c": "ec9d439b-f599-170a-e659-739a0b5034b5",
    "%vlocity_namespace%__IndustryVertical__c": "",
    "%vlocity_namespace%__IsActive__c": true,
    "%vlocity_namespace%__IsPrivate__c": false,
    "%vlocity_namespace%__IsUserAttributesCreatedPrivate__c": false,
    "%vlocity_namespace%__LockedFlg__c": false,
    "%vlocity_namespace%__Status__c": "",
    "%vlocity_namespace%__UIControlType__c": "On-Off",
    "Name": "Marks",
    "VlocityDataPackType": "SObject",
    "VlocityRecordSObjectType": "%vlocity_namespace%__AttributeCategory__c",
    "VlocityRecordSourceKey": "%vlocity_namespace%__AttributeCategory__c/Marks"
}