[
    {
        "%vlocity_namespace%__DomainObjectAPIName__c": "json",
        "%vlocity_namespace%__DomainObjectCreationOrder__c": 1,
        "%vlocity_namespace%__DomainObjectFieldAPIName__c": "attrs:CV Validation result",
        "%vlocity_namespace%__GlobalKey__c": "7f31a12f-4a60-147c-2522-20f1f801e9a7",
        "%vlocity_namespace%__InterfaceFieldAPIName__c": "validation_result",
        "%vlocity_namespace%__IsDisabled__c": false,
        "%vlocity_namespace%__IsRequiredForUpsert__c": false,
        "%vlocity_namespace%__MapId__c": "CV Diagnostics system responseCustom2810",
        "%vlocity_namespace%__UpsertKey__c": false,
        "Name": "CV Diagnostics system response",
        "VlocityDataPackType": "SObject",
        "VlocityRecordSObjectType": "%vlocity_namespace%__DRMapItem__c"
    },
    {
        "%vlocity_namespace%__DomainObjectAPIName__c": "json",
        "%vlocity_namespace%__DomainObjectCreationOrder__c": 1,
        "%vlocity_namespace%__DomainObjectFieldAPIName__c": "id",
        "%vlocity_namespace%__GlobalKey__c": "45629764-4730-c12b-00d9-f0a6236edd4d",
        "%vlocity_namespace%__InterfaceFieldAPIName__c": "id",
        "%vlocity_namespace%__IsDisabled__c": false,
        "%vlocity_namespace%__IsRequiredForUpsert__c": false,
        "%vlocity_namespace%__MapId__c": "CV Diagnostics system responseCustom7889",
        "%vlocity_namespace%__UpsertKey__c": false,
        "Name": "CV Diagnostics system response",
        "VlocityDataPackType": "SObject",
        "VlocityRecordSObjectType": "%vlocity_namespace%__DRMapItem__c"
    }
]