[
    {
        "%vlocity_namespace%__DomainObjectAPIName__c": "json",
        "%vlocity_namespace%__DomainObjectCreationOrder__c": 1,
        "%vlocity_namespace%__DomainObjectFieldAPIName__c": "AssetsM:AssetId",
        "%vlocity_namespace%__FormulaOrder__c": 0,
        "%vlocity_namespace%__GlobalKey__c": "3d97ef88-3656-41e9-9301-5bebc4b3cee6",
        "%vlocity_namespace%__InterfaceFieldAPIName__c": "AssetsMovil:AssetId",
        "%vlocity_namespace%__InterfaceObjectName__c": "json",
        "%vlocity_namespace%__IsDisabled__c": false,
        "%vlocity_namespace%__IsRequiredForUpsert__c": false,
        "%vlocity_namespace%__LinkCreatedIndex__c": 0,
        "%vlocity_namespace%__MapId__c": "ta-care-TransformRadioAvailabilityReconnectionBOCustoma0v6C000000E12lQACItem1",
        "%vlocity_namespace%__TransformValuesMap__c": "{}",
        "%vlocity_namespace%__UpsertKey__c": false,
        "Name": "ta-care-TransformAvailabilityReconnectionBO",
        "VlocityDataPackType": "SObject",
        "VlocityRecordSObjectType": "%vlocity_namespace%__DRMapItem__c"
    },
    {
        "%vlocity_namespace%__DomainObjectAPIName__c": "json",
        "%vlocity_namespace%__DomainObjectCreationOrder__c": 1,
        "%vlocity_namespace%__DomainObjectFieldAPIName__c": "AssetsM:Name",
        "%vlocity_namespace%__FormulaOrder__c": 0,
        "%vlocity_namespace%__GlobalKey__c": "2aee4f7d-5e03-0d08-fb17-a62fc45484fb",
        "%vlocity_namespace%__InterfaceFieldAPIName__c": "AssetsMovil:Name",
        "%vlocity_namespace%__InterfaceObjectName__c": "json",
        "%vlocity_namespace%__IsDisabled__c": false,
        "%vlocity_namespace%__IsRequiredForUpsert__c": false,
        "%vlocity_namespace%__LinkCreatedIndex__c": 0,
        "%vlocity_namespace%__MapId__c": "ta-care-TransformRadioAvailabilityReconnectionBOCustoma0v6C000000E12lQACItem4",
        "%vlocity_namespace%__UpsertKey__c": false,
        "Name": "ta-care-TransformAvailabilityReconnectionBO",
        "VlocityDataPackType": "SObject",
        "VlocityRecordSObjectType": "%vlocity_namespace%__DRMapItem__c"
    },
    {
        "%vlocity_namespace%__DomainObjectAPIName__c": "json",
        "%vlocity_namespace%__DomainObjectCreationOrder__c": 1,
        "%vlocity_namespace%__DomainObjectFieldAPIName__c": "AssetsM:NumberLine",
        "%vlocity_namespace%__FormulaOrder__c": 0,
        "%vlocity_namespace%__GlobalKey__c": "71899632-82ff-3ee0-a468-30fafbfeaf4f",
        "%vlocity_namespace%__InterfaceFieldAPIName__c": "AssetsMovil:NumberLine",
        "%vlocity_namespace%__InterfaceObjectName__c": "json",
        "%vlocity_namespace%__IsDisabled__c": false,
        "%vlocity_namespace%__IsRequiredForUpsert__c": false,
        "%vlocity_namespace%__LinkCreatedIndex__c": 0,
        "%vlocity_namespace%__MapId__c": "ta-care-TransformRadioAvailabilityReconnectionBOCustoma0v6C000000E12lQACItem5",
        "%vlocity_namespace%__UpsertKey__c": false,
        "Name": "ta-care-TransformAvailabilityReconnectionBO",
        "VlocityDataPackType": "SObject",
        "VlocityRecordSObjectType": "%vlocity_namespace%__DRMapItem__c"
    },
    {
        "%vlocity_namespace%__DomainObjectAPIName__c": "json",
        "%vlocity_namespace%__DomainObjectCreationOrder__c": 1,
        "%vlocity_namespace%__DomainObjectFieldAPIName__c": "AssetsM:Status",
        "%vlocity_namespace%__FormulaOrder__c": 0,
        "%vlocity_namespace%__GlobalKey__c": "60cba59f-050f-427f-d7ae-d1be56b098e3",
        "%vlocity_namespace%__InterfaceFieldAPIName__c": "AssetsMovil:Status",
        "%vlocity_namespace%__InterfaceObjectName__c": "json",
        "%vlocity_namespace%__IsDisabled__c": false,
        "%vlocity_namespace%__IsRequiredForUpsert__c": false,
        "%vlocity_namespace%__LinkCreatedIndex__c": 0,
        "%vlocity_namespace%__MapId__c": "ta-care-TransformRadioAvailabilityReconnectionBOCustoma0v6C000000E12lQACItem6",
        "%vlocity_namespace%__UpsertKey__c": false,
        "Name": "ta-care-TransformAvailabilityReconnectionBO",
        "VlocityDataPackType": "SObject",
        "VlocityRecordSObjectType": "%vlocity_namespace%__DRMapItem__c"
    },
    {
        "%vlocity_namespace%__DomainObjectAPIName__c": "json",
        "%vlocity_namespace%__DomainObjectCreationOrder__c": 1,
        "%vlocity_namespace%__DomainObjectFieldAPIName__c": "AssetsM:SubStatus",
        "%vlocity_namespace%__FormulaOrder__c": 0,
        "%vlocity_namespace%__GlobalKey__c": "039c9a4d-87b4-5eb5-865a-a29a742f2bf2",
        "%vlocity_namespace%__InterfaceFieldAPIName__c": "AssetsMovil:SubStatus",
        "%vlocity_namespace%__InterfaceObjectName__c": "json",
        "%vlocity_namespace%__IsDisabled__c": false,
        "%vlocity_namespace%__IsRequiredForUpsert__c": false,
        "%vlocity_namespace%__LinkCreatedIndex__c": 0,
        "%vlocity_namespace%__MapId__c": "ta-care-TransformRadioAvailabilityReconnectionBOCustoma0v6C000000E12lQACItem7",
        "%vlocity_namespace%__UpsertKey__c": false,
        "Name": "ta-care-TransformAvailabilityReconnectionBO",
        "VlocityDataPackType": "SObject",
        "VlocityRecordSObjectType": "%vlocity_namespace%__DRMapItem__c"
    },
    {
        "%vlocity_namespace%__DomainObjectAPIName__c": "json",
        "%vlocity_namespace%__DomainObjectCreationOrder__c": 1,
        "%vlocity_namespace%__DomainObjectFieldAPIName__c": "AssetsM:isValid",
        "%vlocity_namespace%__FormulaOrder__c": 0,
        "%vlocity_namespace%__GlobalKey__c": "a16ce46a-63d7-1cf6-5b64-8c96f15fdd94",
        "%vlocity_namespace%__InterfaceFieldAPIName__c": "AssetsMovil:isValid",
        "%vlocity_namespace%__InterfaceObjectName__c": "json",
        "%vlocity_namespace%__IsDisabled__c": false,
        "%vlocity_namespace%__IsRequiredForUpsert__c": false,
        "%vlocity_namespace%__LinkCreatedIndex__c": 0,
        "%vlocity_namespace%__MapId__c": "ta-care-TransformRadioAvailabilityReconnectionBOCustoma0v6C000000E12lQACItem3",
        "%vlocity_namespace%__UpsertKey__c": false,
        "Name": "ta-care-TransformAvailabilityReconnectionBO",
        "VlocityDataPackType": "SObject",
        "VlocityRecordSObjectType": "%vlocity_namespace%__DRMapItem__c"
    },
    {
        "%vlocity_namespace%__DomainObjectAPIName__c": "json",
        "%vlocity_namespace%__DomainObjectCreationOrder__c": 1,
        "%vlocity_namespace%__DomainObjectFieldAPIName__c": "AssetsM:isValid",
        "%vlocity_namespace%__FormulaOrder__c": 0,
        "%vlocity_namespace%__GlobalKey__c": "da3bf428-5dc4-8364-26a5-581b906d2579",
        "%vlocity_namespace%__InterfaceFieldAPIName__c": "AssetsMovil:isValid",
        "%vlocity_namespace%__InterfaceObjectName__c": "json",
        "%vlocity_namespace%__IsDisabled__c": false,
        "%vlocity_namespace%__IsRequiredForUpsert__c": false,
        "%vlocity_namespace%__LinkCreatedIndex__c": 0,
        "%vlocity_namespace%__MapId__c": "ta-care-TransformRadioAvailabilityReconnectionBOCustoma0v6C000000E12lQACItem2",
        "%vlocity_namespace%__UpsertKey__c": false,
        "Name": "ta-care-TransformAvailabilityReconnectionBO",
        "VlocityDataPackType": "SObject",
        "VlocityRecordSObjectType": "%vlocity_namespace%__DRMapItem__c"
    },
    {
        "%vlocity_namespace%__DomainObjectAPIName__c": "Formula",
        "%vlocity_namespace%__DomainObjectCreationOrder__c": 0,
        "%vlocity_namespace%__DomainObjectFieldAPIName__c": "Formula",
        "%vlocity_namespace%__FormulaOrder__c": 1,
        "%vlocity_namespace%__FormulaResultPath__c": "AssetsMovil:isValid",
        "%vlocity_namespace%__Formula__c": "IF (AssetsMovil:Status = 'Suspended' AND AssetsMovil:SubStatus = 'Administrativo', true, false)",
        "%vlocity_namespace%__GlobalKey__c": "e2b7a2ee-d920-6a21-d56e-12a98986b30f",
        "%vlocity_namespace%__InterfaceObjectName__c": "json",
        "%vlocity_namespace%__IsDisabled__c": false,
        "%vlocity_namespace%__IsRequiredForUpsert__c": false,
        "%vlocity_namespace%__LinkCreatedIndex__c": 0,
        "%vlocity_namespace%__MapId__c": "ta-care-TransformRadioAvailabilityReconnectionBOCustoma0v6C000000E12lQACItem0",
        "%vlocity_namespace%__UpsertKey__c": false,
        "Name": "ta-care-TransformAvailabilityReconnectionBO",
        "VlocityDataPackType": "SObject",
        "VlocityRecordSObjectType": "%vlocity_namespace%__DRMapItem__c"
    }
]