[
    {
        "%vlocity_namespace%__DomainObjectAPIName__c": "json",
        "%vlocity_namespace%__DomainObjectCreationOrder__c": 0,
        "%vlocity_namespace%__DomainObjectFieldAPIName__c": "Asset",
        "%vlocity_namespace%__FilterOperator__c": "=",
        "%vlocity_namespace%__FilterValue__c": "Id",
        "%vlocity_namespace%__FormulaOrder__c": 0,
        "%vlocity_namespace%__GlobalKey__c": "f500e187-8930-0dfd-8cbb-2ba8dc327e6b",
        "%vlocity_namespace%__InterfaceFieldAPIName__c": "Id",
        "%vlocity_namespace%__InterfaceObjectLookupOrder__c": 1,
        "%vlocity_namespace%__InterfaceObjectName__c": "Asset",
        "%vlocity_namespace%__IsDisabled__c": false,
        "%vlocity_namespace%__IsRequiredForUpsert__c": false,
        "%vlocity_namespace%__LinkCreatedIndex__c": 0,
        "%vlocity_namespace%__MapId__c": "getAssetDetailByAssetCustom4233",
        "%vlocity_namespace%__UpsertKey__c": false,
        "Name": "getAssetDetailByAsset",
        "VlocityDataPackType": "SObject",
        "VlocityRecordSObjectType": "%vlocity_namespace%__DRMapItem__c"
    },
    {
        "%vlocity_namespace%__DomainObjectAPIName__c": "json",
        "%vlocity_namespace%__DomainObjectCreationOrder__c": 0,
        "%vlocity_namespace%__DomainObjectFieldAPIName__c": "Account",
        "%vlocity_namespace%__FilterOperator__c": "=",
        "%vlocity_namespace%__FilterValue__c": "Asset:AccountId",
        "%vlocity_namespace%__FormulaOrder__c": 0,
        "%vlocity_namespace%__GlobalKey__c": "76d475a7-ebf3-b29e-d3b8-3d2a84b4b701",
        "%vlocity_namespace%__InterfaceFieldAPIName__c": "Id",
        "%vlocity_namespace%__InterfaceObjectLookupOrder__c": 2,
        "%vlocity_namespace%__InterfaceObjectName__c": "Account",
        "%vlocity_namespace%__IsDisabled__c": false,
        "%vlocity_namespace%__IsRequiredForUpsert__c": false,
        "%vlocity_namespace%__LinkCreatedIndex__c": 0,
        "%vlocity_namespace%__MapId__c": "getAssetDetailByAssetCustom3326",
        "%vlocity_namespace%__UpsertKey__c": false,
        "Name": "getAssetDetailByAsset",
        "VlocityDataPackType": "SObject",
        "VlocityRecordSObjectType": "%vlocity_namespace%__DRMapItem__c"
    },
    {
        "%vlocity_namespace%__DomainObjectAPIName__c": "json",
        "%vlocity_namespace%__DomainObjectCreationOrder__c": 0,
        "%vlocity_namespace%__DomainObjectFieldAPIName__c": "Product",
        "%vlocity_namespace%__FilterOperator__c": "=",
        "%vlocity_namespace%__FilterValue__c": "Asset:Product2Id",
        "%vlocity_namespace%__FormulaOrder__c": 0,
        "%vlocity_namespace%__GlobalKey__c": "bfbf66c1-8ca3-42a0-875a-4e404bf861f6",
        "%vlocity_namespace%__InterfaceFieldAPIName__c": "Id",
        "%vlocity_namespace%__InterfaceObjectLookupOrder__c": 3,
        "%vlocity_namespace%__InterfaceObjectName__c": "Product2",
        "%vlocity_namespace%__IsDisabled__c": false,
        "%vlocity_namespace%__IsRequiredForUpsert__c": false,
        "%vlocity_namespace%__LinkCreatedIndex__c": 0,
        "%vlocity_namespace%__MapId__c": "getAssetDetailByAssetCustom6630",
        "%vlocity_namespace%__UpsertKey__c": false,
        "Name": "getAssetDetailByAsset",
        "VlocityDataPackType": "SObject",
        "VlocityRecordSObjectType": "%vlocity_namespace%__DRMapItem__c"
    },
    {
        "%vlocity_namespace%__DomainObjectAPIName__c": "json",
        "%vlocity_namespace%__DomainObjectCreationOrder__c": 1,
        "%vlocity_namespace%__DomainObjectFieldAPIName__c": "Asset",
        "%vlocity_namespace%__DomainObjectFieldType__c": "List<Map>",
        "%vlocity_namespace%__FormulaOrder__c": 0,
        "%vlocity_namespace%__GlobalKey__c": "6bff0deb-89a4-834e-b050-3b9ee6f734f9",
        "%vlocity_namespace%__IsDisabled__c": false,
        "%vlocity_namespace%__IsRequiredForUpsert__c": false,
        "%vlocity_namespace%__LinkCreatedIndex__c": 0,
        "%vlocity_namespace%__MapId__c": "getAssetDetailByAssetCustom9204",
        "%vlocity_namespace%__UpsertKey__c": false,
        "Name": "getAssetDetailByAsset",
        "VlocityDataPackType": "SObject",
        "VlocityRecordSObjectType": "%vlocity_namespace%__DRMapItem__c"
    },
    {
        "%vlocity_namespace%__DomainObjectAPIName__c": "json",
        "%vlocity_namespace%__DomainObjectCreationOrder__c": 1,
        "%vlocity_namespace%__DomainObjectFieldAPIName__c": "Asset:AccountName",
        "%vlocity_namespace%__FormulaOrder__c": 0,
        "%vlocity_namespace%__GlobalKey__c": "84848985-ee49-f161-57b1-420f81bf8258",
        "%vlocity_namespace%__InterfaceFieldAPIName__c": "Account:Name",
        "%vlocity_namespace%__IsDisabled__c": false,
        "%vlocity_namespace%__IsRequiredForUpsert__c": false,
        "%vlocity_namespace%__LinkCreatedIndex__c": 0,
        "%vlocity_namespace%__MapId__c": "getAssetDetailByAssetCustom5519",
        "%vlocity_namespace%__UpsertKey__c": false,
        "Name": "getAssetDetailByAsset",
        "VlocityDataPackType": "SObject",
        "VlocityRecordSObjectType": "%vlocity_namespace%__DRMapItem__c"
    },
    {
        "%vlocity_namespace%__DomainObjectAPIName__c": "json",
        "%vlocity_namespace%__DomainObjectCreationOrder__c": 1,
        "%vlocity_namespace%__DomainObjectFieldAPIName__c": "Asset:LineNumber",
        "%vlocity_namespace%__FormulaOrder__c": 0,
        "%vlocity_namespace%__GlobalKey__c": "b1775798-14e9-4ecd-b295-36497de48c74",
        "%vlocity_namespace%__InterfaceFieldAPIName__c": "Asset:MSISDN__c",
        "%vlocity_namespace%__IsDisabled__c": false,
        "%vlocity_namespace%__IsRequiredForUpsert__c": false,
        "%vlocity_namespace%__LinkCreatedIndex__c": 0,
        "%vlocity_namespace%__MapId__c": "getAssetDetailByAssetCustom4299",
        "%vlocity_namespace%__UpsertKey__c": false,
        "Name": "getAssetDetailByAsset",
        "VlocityDataPackType": "SObject",
        "VlocityRecordSObjectType": "%vlocity_namespace%__DRMapItem__c"
    },
    {
        "%vlocity_namespace%__DomainObjectAPIName__c": "json",
        "%vlocity_namespace%__DomainObjectCreationOrder__c": 1,
        "%vlocity_namespace%__DomainObjectFieldAPIName__c": "Asset:Name",
        "%vlocity_namespace%__FormulaOrder__c": 0,
        "%vlocity_namespace%__GlobalKey__c": "ccac13d4-44ff-419b-aacc-2fb24ac1b422",
        "%vlocity_namespace%__InterfaceFieldAPIName__c": "Asset:Name",
        "%vlocity_namespace%__IsDisabled__c": false,
        "%vlocity_namespace%__IsRequiredForUpsert__c": false,
        "%vlocity_namespace%__LinkCreatedIndex__c": 0,
        "%vlocity_namespace%__MapId__c": "getAssetDetailByAssetCustom6613",
        "%vlocity_namespace%__UpsertKey__c": false,
        "Name": "getAssetDetailByAsset",
        "VlocityDataPackType": "SObject",
        "VlocityRecordSObjectType": "%vlocity_namespace%__DRMapItem__c"
    },
    {
        "%vlocity_namespace%__DomainObjectAPIName__c": "json",
        "%vlocity_namespace%__DomainObjectCreationOrder__c": 1,
        "%vlocity_namespace%__DomainObjectFieldAPIName__c": "Asset:ProductName",
        "%vlocity_namespace%__FormulaOrder__c": 0,
        "%vlocity_namespace%__GlobalKey__c": "5fe4ccb5-7b33-dd50-aa25-3b7a2e07018b",
        "%vlocity_namespace%__InterfaceFieldAPIName__c": "Product:Name",
        "%vlocity_namespace%__IsDisabled__c": false,
        "%vlocity_namespace%__IsRequiredForUpsert__c": false,
        "%vlocity_namespace%__LinkCreatedIndex__c": 0,
        "%vlocity_namespace%__MapId__c": "getAssetDetailByAssetCustom6005",
        "%vlocity_namespace%__UpsertKey__c": false,
        "Name": "getAssetDetailByAsset",
        "VlocityDataPackType": "SObject",
        "VlocityRecordSObjectType": "%vlocity_namespace%__DRMapItem__c"
    },
    {
        "%vlocity_namespace%__DefaultValue__c": "''",
        "%vlocity_namespace%__DomainObjectAPIName__c": "json",
        "%vlocity_namespace%__DomainObjectCreationOrder__c": 1,
        "%vlocity_namespace%__DomainObjectFieldAPIName__c": "Asset:Status",
        "%vlocity_namespace%__FormulaOrder__c": 0,
        "%vlocity_namespace%__GlobalKey__c": "a80953b5-4ad9-c18a-60fe-3cedeb04e8eb",
        "%vlocity_namespace%__InterfaceFieldAPIName__c": "Asset:Status",
        "%vlocity_namespace%__IsDisabled__c": false,
        "%vlocity_namespace%__IsRequiredForUpsert__c": false,
        "%vlocity_namespace%__LinkCreatedIndex__c": 0,
        "%vlocity_namespace%__MapId__c": "getAssetDetailByAssetCustom116",
        "%vlocity_namespace%__UpsertKey__c": false,
        "Name": "getAssetDetailByAsset",
        "VlocityDataPackType": "SObject",
        "VlocityRecordSObjectType": "%vlocity_namespace%__DRMapItem__c"
    }
]