{
    "%vlocity_namespace%__CalculationMatrixId__c": {
        "Name": "RAVExceptionMatrix",
        "VlocityDataPackType": "VlocityMatchingKeyObject",
        "VlocityMatchingRecordSourceKey": "%vlocity_namespace%__CalculationMatrix__c/RAVExceptionMatrix",
        "VlocityRecordSObjectType": "%vlocity_namespace%__CalculationMatrix__c"
    },
    "%vlocity_namespace%__CalculationMatrixId__r.Name": "RAVExceptionMatrix",
    "%vlocity_namespace%__CalculationMatrixRow__c": "RAVExceptionMatrix_Version_Rows.json",
    "%vlocity_namespace%__CurrentStatus__c": "Active",
    "%vlocity_namespace%__EndDateTime__c": "",
    "%vlocity_namespace%__GlobalKey__c": "41c7ab13-f242-a492-ca13-cc47ab0de6ef",
    "%vlocity_namespace%__Priority__c": 1,
    "%vlocity_namespace%__StartDateTime__c": "2018-02-08T15:42:21.000Z",
    "%vlocity_namespace%__VersionNumber__c": 1,
    "Name": "RAVExceptionMatrix",
    "VlocityDataPackType": "SObject",
    "VlocityRecordSObjectType": "%vlocity_namespace%__CalculationMatrixVersion__c",
    "VlocityRecordSourceKey": "%vlocity_namespace%__CalculationMatrixVersion__c/RAVExceptionMatrix"
}